atmoflux/__init__.py
atmoflux/aerosols.py
atmoflux/balance.py
atmoflux/constants.py
atmoflux/core.py
atmoflux/humidity.py
atmoflux/hydro.py
atmoflux/radiative.py
atmoflux/temperature.py
atmoflux/turbulent.py
atmoflux/wind.py
atmoflux-0.1.0.dist-info/licenses/LICENSE
atmoflux-0.1.0.dist-info/METADATA
atmoflux-0.1.0.dist-info/WHEEL
atmoflux-0.1.0.dist-info/top_level.txt
atmoflux-0.1.0.dist-info/RECORD
