Metadata-Version: 2.4
Name: atmoflux
Version: 0.1.0
Summary: Atmospheric and energy flux analysis library by Telluris Labs
Author-email: Telluris Labs <info@tellurislabs.io>
License: MIT
Project-URL: Homepage, https://tellurislabs.io
Keywords: atmospheric science,climate science,micrometeorology,surface energy balance,land-atmosphere exchange,energy fluxes,radiative fluxes,turbulent fluxes,hydrological fluxes,boundary layer,urban climate
Classifier: Programming Language :: Python :: 3
Classifier: Operating System :: OS Independent
Classifier: Intended Audience :: Science/Research
Classifier: Topic :: Scientific/Engineering :: Atmospheric Science
Classifier: Topic :: Scientific/Engineering :: Hydrology
Requires-Python: >=3.9
License-File: LICENSE
Requires-Dist: numpy>=1.22
Dynamic: license-file
